[{"line":2,"elements":[{"start_timestamp":"2024-05-17T19:49:28.903Z","line":9,"name":"scroll to element text","description":"","id":"scroll;scroll-to-element-text","type":"scenario","keyword":"Scenario","steps":[{"result":{"duration":6358351500,"status":"passed"},"line":10,"name":"go to main page","match":{"location":"stepdefinitions.Day_03_KeyEvents_ScreenLock_StepDef.goToMainPage()"},"keyword":"Given "},{"result":{"duration":232195900,"status":"passed"},"line":11,"name":"click on api demos apk","match":{"location":"stepdefinitions.Day_06_Scroll_Top_Scroll_Text_StepDef.clickOnApiDemosApk()"},"keyword":"And "},{"result":{"duration":2478673800,"status":"passed"},"line":12,"name":"click on views","match":{"location":"stepdefinitions.Day_04_LongClick_DragDrop_StepDef.clickOnViews()"},"keyword":"And "},{"result":{"duration":3360562500,"status":"passed"},"line":13,"name":"scroll to rotating button","match":{"location":"stepdefinitions.Day_06_Scroll_Top_Scroll_Text_StepDef.scrollToRotatingButton()"},"keyword":"And "}],"tags":[{"name":"@scrollTop_Text"}]}],"name":"Scroll","description":"","id":"scroll","keyword":"Feature","uri":"file:src/test/resources/features/day_06_Scroll_Top_Scroll_Text.feature","tags":[]}]